Metadata-Version: 2.1
Name: torchgaussianfilter
Version: 0.0.2
Summary: Gaussian filtering using PyTorch
Home-page: http://github.com/masadcv/torchgaussianfilter
Author: Muhammad Asad
Author-email: masadcv@gmail.com
License: BSD-3-Clause
Keywords: gaussian filtering 2d 3d medical features hand-crafted
Platform: UNKNOWN
Classifier: Operating System :: OS Independent
Classifier: License :: OSI Approved :: BSD License
Classifier: Programming Language :: Python :: 3
